Metadata-Version: 2.1
Name: odoo14-addon-product_supplierinfo_for_customer_sale
Version: 14.0.1.3.0
Summary: Loads in every sale order line the customer code defined in the product
Home-page: https://github.com/OCA/sale-workflow
Author: Agile Business Group,Vauxoo,Odoo Community Association (OCA)
Author-email: support@odoo-community.org
License: AGPL-3
Classifier: Programming Language :: Python
Classifier: Framework :: Odoo
Classifier: Framework :: Odoo :: 14.0
Classifier: License :: OSI Approved :: GNU Affero General Public License v3
Requires-Python: >=3.6
Requires-Dist: odoo14-addon-product-supplierinfo-for-customer
Requires-Dist: odoo<14.1dev,>=14.0a
